postgresdbdiff.py
postgres_db_diff-0.9.1.dist-info/DESCRIPTION.rst
postgres_db_diff-0.9.1.dist-info/METADATA
postgres_db_diff-0.9.1.dist-info/RECORD
postgres_db_diff-0.9.1.dist-info/WHEEL
postgres_db_diff-0.9.1.dist-info/entry_points.txt
postgres_db_diff-0.9.1.dist-info/metadata.json
postgres_db_diff-0.9.1.dist-info/top_level.txt
