Metadata-Version: 2.0
Name: postgres-db-diff
Version: 0.9.1
Summary: Command line tool to compare two PostgreSQL databases
Home-page: https://github.com/petraszd/postgres-db-diff
Author: Petras Zdanavicius
Author-email: petraszd@gmail.com
License: UNKNOWN
Keywords: postgresql database comparison command line utility
Platform: UNKNOWN
Classifier: Environment :: Console
Classifier: License :: OSI Approved :: MIT License
Classifier: Topic :: Utilities
Classifier: Programming Language :: Python :: 2
Classifier: Programming Language :: Python :: 2.7
Classifier: Programming Language :: Python :: 3
Classifier: Programming Language :: Python :: 3.4
Classifier: Programming Language :: Python :: 3.5
Classifier: Programming Language :: Python :: 3.6
Provides-Extra: dev
Provides-Extra: test
